convst/__init__.py
convst/classifiers/__init__.py
convst/classifiers/rdst_ensemble.py
convst/classifiers/rdst_ridge.py
convst/interpreters/__init__.py
convst/interpreters/rdst_interpreter.py
convst/transformers/__init__.py
convst/transformers/_commons.py
convst/transformers/_input_transformers.py
convst/transformers/_multivariate_same_length.py
convst/transformers/_multivariate_variable_length.py
convst/transformers/_univariate_same_length.py
convst/transformers/_univariate_variable_length.py
convst/transformers/rdst.py
convst/utils/__init__.py
convst/utils/checks_utils.py
convst/utils/dataset_utils.py
convst/utils/experiments_utils.py
convst/utils/numba_utils.py
convst/utils/plot_utils.py
convst-0.3.1.dist-info/LICENSE
convst-0.3.1.dist-info/METADATA
convst-0.3.1.dist-info/WHEEL
convst-0.3.1.dist-info/top_level.txt
convst-0.3.1.dist-info/RECORD
