Metadata-Version: 2.1
Name: convst
Version: 0.3.1
Summary: The Random Dilation Shapelet Transform algorithm and associated works
Home-page: https://github.com/baraline/convst
Download-URL: https://pypi.org/project/convst/#files
Author: Antoine Guillaume
Author-email: Antoine Guillaume <antoine.guillaume45@gmail.com>
License: BSD 2-Clause License
Project-URL: repository, https://github.com/baraline/convst
Project-URL: documentation, https://convst.readthedocs.io/
Project-URL: download, https://pypi.org/project/convst/#files
Keywords: data-science,machine-learning,data-mining,time-series,shapelets,time-series-classification
Classifier: Intended Audience :: Science/Research
Classifier: Intended Audience :: Developers
Classifier: License :: OSI Approved :: BSD License
Classifier: Programming Language :: Python
Classifier: Topic :: Software Development
Classifier: Topic :: Scientific/Engineering
Classifier: Operating System :: Microsoft :: Windows
Classifier: Operating System :: POSIX
Classifier: Operating System :: Unix
Classifier: Operating System :: MacOS
Classifier: Programming Language :: Python :: 3.8
Classifier: Programming Language :: Python :: 3.9
Classifier: Programming Language :: Python :: 3.10
Classifier: Programming Language :: Python :: 3.11
Requires-Python: >=3.8,<3.12
License-File: LICENSE
Requires-Dist: aeon (>=0.4)
Requires-Dist: numba (>=0.55)
Requires-Dist: numpy (<1.25,>=1.21.0)
Requires-Dist: scikit-learn (<1.3.0,>=1.0.0)
Requires-Dist: scipy (<2.0.0,>=1.2.0)
Requires-Dist: pandas (<1.6.0,>=1.1.0)
Requires-Dist: joblib (>=1.1.1)
Requires-Dist: matplotlib (>=3.3.2)
Requires-Dist: seaborn (>=0.11.0)
Requires-Dist: pytest (>=7.0)
Requires-Dist: sphinx (>=4.2.0)
Requires-Dist: sphinx-gallery (>=0.10.1)
Requires-Dist: numpydoc (>=1.1.0)
Requires-Dist: alabaster (>=0.7.12)
